aiogram/__init__.py
aiogram/__main__.py
aiogram/bot/__init__.py
aiogram/bot/api.py
aiogram/bot/base.py
aiogram/bot/bot.py
aiogram/contrib/__init__.py
aiogram/contrib/fsm_storage/__init__.py
aiogram/contrib/fsm_storage/files.py
aiogram/contrib/fsm_storage/memory.py
aiogram/contrib/fsm_storage/mongo.py
aiogram/contrib/fsm_storage/redis.py
aiogram/contrib/fsm_storage/rethinkdb.py
aiogram/contrib/middlewares/__init__.py
aiogram/contrib/middlewares/environment.py
aiogram/contrib/middlewares/fsm.py
aiogram/contrib/middlewares/i18n.py
aiogram/contrib/middlewares/logging.py
aiogram/dispatcher/__init__.py
aiogram/dispatcher/dispatcher.py
aiogram/dispatcher/handler.py
aiogram/dispatcher/middlewares.py
aiogram/dispatcher/storage.py
aiogram/dispatcher/webhook.py
aiogram/dispatcher/filters/__init__.py
aiogram/dispatcher/filters/builtin.py
aiogram/dispatcher/filters/factory.py
aiogram/dispatcher/filters/filters.py
aiogram/dispatcher/filters/state.py
aiogram/types/__init__.py
aiogram/types/animation.py
aiogram/types/audio.py
aiogram/types/auth_widget_data.py
aiogram/types/base.py
aiogram/types/bot_command.py
aiogram/types/bot_command_scope.py
aiogram/types/callback_game.py
aiogram/types/callback_query.py
aiogram/types/chat.py
aiogram/types/chat_administrator_rights.py
aiogram/types/chat_invite_link.py
aiogram/types/chat_join_request.py
aiogram/types/chat_location.py
aiogram/types/chat_member.py
aiogram/types/chat_member_updated.py
aiogram/types/chat_permissions.py
aiogram/types/chat_photo.py
aiogram/types/chat_shared.py
aiogram/types/chosen_inline_result.py
aiogram/types/contact.py
aiogram/types/dice.py
aiogram/types/document.py
aiogram/types/encrypted_credentials.py
aiogram/types/encrypted_passport_element.py
aiogram/types/fields.py
aiogram/types/file.py
aiogram/types/force_reply.py
aiogram/types/forum_topic.py
aiogram/types/forum_topic_closed.py
aiogram/types/forum_topic_created.py
aiogram/types/forum_topic_edited.py
aiogram/types/forum_topic_reopened.py
aiogram/types/game.py
aiogram-2.25.2.dist-info/LICENSE
aiogram-2.25.2.dist-info/METADATA
aiogram-2.25.2.dist-info/WHEEL
aiogram-2.25.2.dist-info/top_level.txt
aiogram-2.25.2.dist-info/RECORD
