Metadata-Version: 2.1
Name: aiogram
Version: 2.25.2
Summary: Is a pretty simple and fully asynchronous framework for Telegram Bot API
Home-page: https://github.com/aiogram/aiogram
Author: Alex Root Junior
Author-email: jroot.junior@gmail.com
License: MIT
Platform: UNKNOWN
Classifier: Development Status :: 5 - Production/Stable
Classifier: Environment :: Console
Classifier: Framework :: AsyncIO
Classifier: Intended Audience :: Developers
Classifier: Intended Audience :: System Administrators
Classifier: License :: OSI Approved :: MIT License
Classifier: Programming Language :: Python :: 3.7
Classifier: Programming Language :: Python :: 3.8
Classifier: Programming Language :: Python :: 3.9
Classifier: Programming Language :: Python :: 3.10
Classifier: Topic :: Software Development :: Libraries :: Application Frameworks
Requires-Python: >=3.7
Provides-Extra: proxy
Provides-Extra: fast
License-File: LICENSE
